perspectives/DataFrame.py
perspectives/__init__.py
perspectives-1.0.4.dist-info/LICENSE
perspectives-1.0.4.dist-info/METADATA
perspectives-1.0.4.dist-info/WHEEL
perspectives-1.0.4.dist-info/top_level.txt
perspectives-1.0.4.dist-info/RECORD
